{
    "Name":  "DependencyManager-ErrorCases.Tests",
    "Path":  "D:\\DO\\WEB\\N8N_tests\\PROJETS\\EMAIL_SENDER_1\\scripts\\utils\\PSCacheManager\\PredictiveCache\\Tests\\DependencyManager-ErrorCases.Tests.ps1",
    "Category":  "PredictiveCache",
    "Priority":  400,
    "RegisteredDate":  {
                           "value":  "\/Date(1744554603858)\/",
                           "DisplayHint":  2,
                           "DateTime":  "dimanche 13 avril 2025 16:30:03"
                       }
}
